pytalog/base/__init__.py
pytalog/base/catalog/__init__.py
pytalog/base/catalog/catalog.py
pytalog/base/catalog/dataset.py
pytalog/base/configuration/__init__.py
pytalog/base/configuration/config.py
pytalog/base/data_sources/__init__.py
pytalog/base/data_sources/data.py
pytalog/base/data_sources/data_source.py
pytalog/base/utils/__init__.py
pytalog/base/utils/load_object.py
pytalog/base/utils/load_yaml.py
pytalog/base/utils/logger.py
pytalog/base/validation/__init__.py
pytalog/base/validation/validation_set.py
pytalog/base/validation/validator.py
pytalog_base-0.1.1.dist-info/METADATA
pytalog_base-0.1.1.dist-info/WHEEL
pytalog_base-0.1.1.dist-info/top_level.txt
pytalog_base-0.1.1.dist-info/RECORD
