Metadata-Version: 2.1
Name: pytalog-base
Version: 0.1.1
Requires-Python: >=3.9,<3.12
Requires-Dist: PyYAML==6.0.1
Requires-Dist: jinja2==3.1.2
Provides-Extra: dev
Requires-Dist: PyYAML==6.0.1; extra == "dev"
Requires-Dist: jinja2==3.1.2; extra == "dev"
Requires-Dist: pre-commit; extra == "dev"
Requires-Dist: build==0.8.0; extra == "dev"
Requires-Dist: pypiserver==1.5.1; extra == "dev"
Requires-Dist: twine==4.0.1; extra == "dev"
Requires-Dist: pdoc==13.1.0; extra == "dev"
Requires-Dist: importlib-metadata<8.0.0; extra == "dev"
Requires-Dist: pytest; extra == "dev"
Requires-Dist: pytest-cov; extra == "dev"
Provides-Extra: strict
Requires-Dist: PyYAML==6.0.1; extra == "strict"
Requires-Dist: jinja2==3.1.2; extra == "strict"
Provides-Extra: test
Requires-Dist: PyYAML==6.0.1; extra == "test"
Requires-Dist: jinja2==3.1.2; extra == "test"
Requires-Dist: pytest; extra == "test"
Requires-Dist: pytest-cov; extra == "test"
